setup.py
distributions_20220712/Binomialdistribution.py
distributions_20220712/Gaussiandistribution.py
distributions_20220712/Generaldistribution.py
distributions_20220712/__init__.py
distributions_20220712.egg-info/PKG-INFO
distributions_20220712.egg-info/SOURCES.txt
distributions_20220712.egg-info/dependency_links.txt
distributions_20220712.egg-info/not-zip-safe
distributions_20220712.egg-info/top_level.txt